toposolve/_toposolve.cpp
toposolve/__init__.py
toposolve/_toposolve.cpython-312-darwin.so
toposolve-0.1.17.dist-info/RECORD
toposolve-0.1.17.dist-info/LICENSE
toposolve-0.1.17.dist-info/WHEEL
toposolve-0.1.17.dist-info/top_level.txt
toposolve-0.1.17.dist-info/METADATA
