Metadata-Version: 2.1
Name: toposolve
Version: 0.1.17
Summary: A fast C++ implementation of the Held-Karp algorithm for solving TSP
Author-email: Jack Min Ong <ongjackm@gmail.com>
License: MIT
Classifier: Programming Language :: Python :: 3
Classifier: License :: OSI Approved :: MIT License
Classifier: Operating System :: OS Independent
Requires-Python: >=3.8
License-File: LICENSE
Requires-Dist: pybind11>=2.6.0
